xtuner/__init__.py
xtuner/entry_point.py
xtuner/registry.py
xtuner/version.py
xtuner/_lite/__init__.py
xtuner/_lite/device.py
xtuner/_lite/accelerate/__init__.py
xtuner/_lite/accelerate/lora.py
xtuner/_lite/accelerate/packed.py
xtuner/_lite/accelerate/utils.py
xtuner/_lite/accelerate/ops/__init__.py
xtuner/_lite/accelerate/ops/moe_permute.py
xtuner/_lite/algorithms/__init__.py
xtuner/_lite/algorithms/ppo/__init__.py
xtuner/_lite/algorithms/ppo/dataset.py
xtuner/_lite/algorithms/ppo/loss.py
xtuner/_lite/algorithms/ppo/model.py
xtuner/_lite/algorithms/sft/__init__.py
xtuner/_lite/algorithms/sft/dataset.py
xtuner/_lite/chat/__init__.py
xtuner/_lite/chat/backends/__init__.py
xtuner/_lite/chat/messages/__init__.py
xtuner/_lite/chat/messages/base.py
xtuner/_lite/chat/messages/chat.py
xtuner/_lite/chat/templates/__init__.py
xtuner/_lite/chat/templates/chat.py
xtuner/_lite/chat/templates/hybrid.py
xtuner/_lite/datasets/__init__.py
xtuner/_lite/datasets/json.py
xtuner/_lite/datasets/jsonl.py
xtuner/_lite/datasets/pack.py
xtuner/_lite/datasets/streaming.py
xtuner/_lite/datasets/utils/__init__.py
xtuner/_lite/datasets/utils/convert.py
xtuner/_lite/datasets/utils/load.py
xtuner/_lite/datasets/utils/utils.py
xtuner/_lite/modelings/__init__.py
xtuner/_lite/modelings/internlm2/__init__.py
xtuner/_lite/modelings/internlm2/configuration_internlm2.py
xtuner/_lite/modelings/internlm2/modeling_internlm2.py
xtuner/_lite/modelings/internlm3/__init__.py
xtuner/_lite/modelings/internlm3/configuration_internlm3.py
xtuner/_lite/modelings/internlm3/modeling_internlm3.py
xtuner/_lite/modelings/internlm3/tokenization_internlm3.py
xtuner/_lite/modelings/internvl2/__init__.py
xtuner/_lite/modelings/internvl2/configuration_intern_vit.py
xtuner/_lite/modelings/internvl2/modeling_intern_vit.py
xtuner/_lite/modelings/llava/__init__.py
xtuner/_lite/modelings/llava/configuration_internlm2.py
xtuner/_lite/modelings/llava/configuration_llava.py
xtuner/_lite/modelings/llava/modeling_internlm2.py
xtuner-0.2.0.dist-info/LICENSE
xtuner-0.2.0.dist-info/METADATA
xtuner-0.2.0.dist-info/WHEEL
xtuner-0.2.0.dist-info/entry_points.txt
xtuner-0.2.0.dist-info/top_level.txt
xtuner-0.2.0.dist-info/RECORD
