Metadata-Version: 2.1
Name: xtuner
Version: 0.2.0
Summary: An efficient, flexible and full-featured toolkit for fine-tuning large models
Home-page: https://github.com/InternLM/xtuner
Author: XTuner Contributors
Author-email: openmmlab@gmail.com
License: Apache License 2.0
Keywords: large language model,parameter-efficient fine-tuning
Platform: UNKNOWN
Classifier: Development Status :: 4 - Beta
Classifier: License :: OSI Approved :: Apache Software License
Classifier: Operating System :: OS Independent
Classifier: Programming Language :: Python :: 3
Classifier: Programming Language :: Python :: 3.8
Classifier: Programming Language :: Python :: 3.9
Classifier: Programming Language :: Python :: 3.10
Classifier: Programming Language :: Python :: 3.11
Classifier: Programming Language :: Python :: 3.12
Classifier: Topic :: Utilities
Requires-Python: >=3.8, <3.13
Requires-Dist: bitsandbytes==0.45.0
Requires-Dist: datasets>=3.2.0
Requires-Dist: einops
Requires-Dist: loguru
Requires-Dist: mmengine==0.10.6
Requires-Dist: openpyxl
Requires-Dist: peft>=0.14.0
Requires-Dist: scikit-image
Requires-Dist: scipy
Requires-Dist: SentencePiece
Requires-Dist: tiktoken
Requires-Dist: torch
Requires-Dist: torchvision
Requires-Dist: transformers==4.48.0
Requires-Dist: transformers-stream-generator
Provides-Extra: all
Requires-Dist: bitsandbytes==0.45.0; extra == "all"
Requires-Dist: datasets>=3.2.0; extra == "all"
Requires-Dist: einops; extra == "all"
Requires-Dist: loguru; extra == "all"
Requires-Dist: mmengine==0.10.6; extra == "all"
Requires-Dist: openpyxl; extra == "all"
Requires-Dist: peft>=0.14.0; extra == "all"
Requires-Dist: scikit-image; extra == "all"
Requires-Dist: scipy; extra == "all"
Requires-Dist: SentencePiece; extra == "all"
Requires-Dist: tiktoken; extra == "all"
Requires-Dist: torch; extra == "all"
Requires-Dist: torchvision; extra == "all"
Requires-Dist: transformers==4.48.0; extra == "all"
Requires-Dist: transformers-stream-generator; extra == "all"
Requires-Dist: deepspeed==0.16.2; extra == "all"
Requires-Dist: mpi4py-mpich; extra == "all"
Requires-Dist: modelscope; extra == "all"
Provides-Extra: deepspeed
Requires-Dist: bitsandbytes==0.45.0; extra == "deepspeed"
Requires-Dist: datasets>=3.2.0; extra == "deepspeed"
Requires-Dist: einops; extra == "deepspeed"
Requires-Dist: loguru; extra == "deepspeed"
Requires-Dist: mmengine==0.10.6; extra == "deepspeed"
Requires-Dist: openpyxl; extra == "deepspeed"
Requires-Dist: peft>=0.14.0; extra == "deepspeed"
Requires-Dist: scikit-image; extra == "deepspeed"
Requires-Dist: scipy; extra == "deepspeed"
Requires-Dist: SentencePiece; extra == "deepspeed"
Requires-Dist: tiktoken; extra == "deepspeed"
Requires-Dist: torch; extra == "deepspeed"
Requires-Dist: torchvision; extra == "deepspeed"
Requires-Dist: transformers==4.48.0; extra == "deepspeed"
Requires-Dist: transformers-stream-generator; extra == "deepspeed"
Requires-Dist: deepspeed==0.16.2; extra == "deepspeed"
Requires-Dist: mpi4py-mpich; extra == "deepspeed"
Provides-Extra: modelscope
Requires-Dist: bitsandbytes==0.45.0; extra == "modelscope"
Requires-Dist: datasets>=3.2.0; extra == "modelscope"
Requires-Dist: einops; extra == "modelscope"
Requires-Dist: loguru; extra == "modelscope"
Requires-Dist: mmengine==0.10.6; extra == "modelscope"
Requires-Dist: openpyxl; extra == "modelscope"
Requires-Dist: peft>=0.14.0; extra == "modelscope"
Requires-Dist: scikit-image; extra == "modelscope"
Requires-Dist: scipy; extra == "modelscope"
Requires-Dist: SentencePiece; extra == "modelscope"
Requires-Dist: tiktoken; extra == "modelscope"
Requires-Dist: torch; extra == "modelscope"
Requires-Dist: torchvision; extra == "modelscope"
Requires-Dist: transformers==4.48.0; extra == "modelscope"
Requires-Dist: transformers-stream-generator; extra == "modelscope"
Requires-Dist: modelscope; extra == "modelscope"
